QrCodeTransfer/__init__.py
QrCodeTransfer/__main__.py
QrCodeTransfer/list.py
QrCodeTransfer/packet.py
QrCodeTransfer/receiver.py
QrCodeTransfer/scanner.py
QrCodeTransfer/sender.py
qrcodetransfer-0.1.1.dist-info/LICENSE
qrcodetransfer-0.1.1.dist-info/WHEEL
qrcodetransfer-0.1.1.dist-info/METADATA
qrcodetransfer-0.1.1.dist-info/RECORD
